atlas_engine_client/__init__.py
atlas_engine_client/client_factory.py
atlas_engine_client/app_info/__init__.py
atlas_engine_client/app_info/app_info_client.py
atlas_engine_client/core/__init__.py
atlas_engine_client/core/base_client.py
atlas_engine_client/core/loop_helper.py
atlas_engine_client/core/api/__init__.py
atlas_engine_client/core/api/base_client.py
atlas_engine_client/core/api/client.py
atlas_engine_client/core/api/helpers/__init__.py
atlas_engine_client/core/api/helpers/application_info.py
atlas_engine_client/core/api/helpers/data_object_instances.py
atlas_engine_client/core/api/helpers/empty_tasks.py
atlas_engine_client/core/api/helpers/events.py
atlas_engine_client/core/api/helpers/external_tasks.py
atlas_engine_client/core/api/helpers/flow_node_instances.py
atlas_engine_client/core/api/helpers/manual_tasks.py
atlas_engine_client/core/api/helpers/process_definitions.py
atlas_engine_client/core/api/helpers/process_instances.py
atlas_engine_client/core/api/helpers/process_models.py
atlas_engine_client/core/api/helpers/user_tasks.py
atlas_engine_client/event/__init__.py
atlas_engine_client/event/event_client.py
atlas_engine_client/external_task/__init__.py
atlas_engine_client/external_task/client_wrapper.py
atlas_engine_client/external_task/external_task_client.py
atlas_engine_client/external_task/external_task_worker.py
atlas_engine_client/external_task/functional_error.py
atlas_engine_client/flow_node_instance/__init__.py
atlas_engine_client/flow_node_instance/flow_node_instance_client.py
atlas_engine_client/notification/__init__.py
atlas_engine_client/notification/notification_client.py
atlas_engine_client/process_definition/__init__.py
atlas_engine_client/process_definition/process_definition_client.py
atlas_engine_client/process_definition/start_callback_type.py
atlas_engine_client/process_instance/__init__.py
atlas_engine_client/process_instance/process_instance_client.py
atlas_engine_client/user_task/__init__.py
atlas_engine_client-3.1.2.dist-info/METADATA
atlas_engine_client-3.1.2.dist-info/WHEEL
atlas_engine_client-3.1.2.dist-info/top_level.txt
atlas_engine_client-3.1.2.dist-info/RECORD
