Metadata-Version: 2.1
Name: atlas-engine-client
Version: 3.1.2
Summary: A Client for the workflow engine of the ProcessCube platform.
Home-page: https://github.com/atlas-engine/Client.py
Author: 5Minds IT-Solutions GmbH & Co. KG
Author-email: ProcessCube@5Minds.de
Keywords: workflow-engine atlas-engine client bpmn
Classifier: Programming Language :: Python :: 3
Classifier: License :: OSI Approved :: MIT License
Classifier: Operating System :: OS Independent
Requires-Dist: aiohttp ==3.8.3
Requires-Dist: nest-asyncio ==1.5.6
Requires-Dist: dataclasses-json >=0.5.7
Requires-Dist: requests >=2.28.1
